{
  "maps": [
    {
      "mapId": "vn",
      "name": "Vietnam",
      "time": "2026-3-13",
      "description": "Map data was obtained from [OpenStreetMap Data Extracts](https://download.geofabrik.de/).",
      "sizeInBytes": 757657149,
      "continent": "Asia",
      "allow": true
    },
    {
      "mapId": "tr",
      "name": "Turkey",
      "time": "2026-04-26",
      "description": "Map data was obtained from [OpenStreetMap Data Extracts](https://download.geofabrik.de/).",
      "sizeInBytes": 1287184575,
      "continent": "Europe",
      "allow": true
    },
    {
      "mapId": "in_central",
      "name": "India (Central Zone)",
      "time": "2026-04-28",
      "description": "Map data was obtained from [OpenStreetMap Data Extracts](https://download.geofabrik.de/). This area includes Uttar Pradesh, Madhya Pradesh, Chhattisgarh, and Uttarakhand.",
      "sizeInBytes": 807421807,
      "continent": "Asia",
      "allow": true
    },
    {
      "mapId": "in",
      "name": "India (Full Map)",
      "time": "2026-04-28",
      "description": "Map data was obtained from [OpenStreetMap Data Extracts](https://download.geofabrik.de/).",
      "sizeInBytes": 3757961188,
      "continent": "Asia",
      "allow": true
    },
    {
      "mapId": "la",
      "name": "Laos",
      "time": "",
      "description": "Map data was obtained from [OpenStreetMap Data Extracts](https://download.geofabrik.de/).",
      "sizeInBytes": 0,
      "continent": "Asia",
      "allow": false
    },
    {
      "mapId": "th",
      "name": "Thailand",
      "time": "",
      "description": "Map data was obtained from [OpenStreetMap Data Extracts](https://download.geofabrik.de/).",
      "sizeInBytes": 0,
      "continent": "Asia",
      "allow": false
    },
    {
      "mapId": "jp",
      "name": "Japan",
      "time": "",
      "description": "Map data was obtained from [OpenStreetMap Data Extracts](https://download.geofabrik.de/).",
      "sizeInBytes": 0,
      "continent": "Asia",
      "allow": false
    },
    {
      "mapId": "sg",
      "name": "Singapore",
      "time": "",
      "description": "Map data was obtained from [OpenStreetMap Data Extracts](https://download.geofabrik.de/).",
      "sizeInBytes": 0,
      "continent": "Asia",
      "allow": false
    }
  ]
}
